Workbook

Sheet Inicio
A1: Ejercicio tienda — ETL y EDA
A2: Base de ventas y compras completada a 10 registros, limpiada y analizada.
A4: Mapa del libro
A5: Inventario | B5: Productos, presupuesto y balance de la tienda.
A6: Ventas | B6: 10 registros de ventas (5 originales + 5 nuevos con errores).
A7: Compras | B7: 10 registros de compras (5 originales + 5 nuevos con errores).
A8: ETL | B8: Tablas de ventas y compras ya limpias.
A9: EDA | B9: Resumen, ganancia por producto y gasto por producto.
A10: Conclusiones | B10: Hallazgos del ejercicio.
A12: Leyenda de colores
A13: Texto azul | B13: Dato de entrada (base cruda).
A14: Texto negro | B14: Resultado calculado con fórmula.
A15: Celda amarilla | B15: Conclusión escrita por la estudiante.

Sheet Inventario
A1: Producto | B1: inventario | C1: costo | D1: venta | E1: Inventario nuevo
A2: galletas chocolate | B2: 7 | C2: 1.5 | D2: =C2*2 -> 3 | E2: =B2-Ventas!C4 -> 5
A3: galletas mms chocolate | B3: 7 | C3: 2 | D3: =C3*2 -> 4
A4: galleta red velvet chocolate | B4: 7 | C4: 2 | D4: =C4*2 -> 4 | E4: =B4-Ventas!C3 -> 6
A5: cinamonroll | B5: 2 | C5: 4 | D5: =C5*2 -> 8
A6: tiramisu | B6: 2 | C6: 4 | D6: =C6*2 -> 8 | E6: =B6-Ventas!C2 -> 0
A7: cheese cake arandanos | B7: 2 | C7: 4 | D7: =C7*2 -> 8
A8: cheese cake cereza | B8: 2 | C8: 4 | D8: =C8*2 -> 8
B10: =SUM(Ventas!G2:G11) -> 70
A11: Presupuesto inicial | B11: =SUM(Compras!E2:E11) -> 68
A12: Total Ventas | B12: =B9+B10-B11 -> 2
A13: Total Compras | B13: =SUM(Compras!E2:E6) -> 35.5
A14: Balance final | B14: =B11+B12-B13 -> 34.5

Sheet Ventas
A1: id venta | B1: Producto | C1: Cantidad | D1: Costo U | E1: Costo Total | F1: Precio U | G1: Precio total | H1: Ganancia
A2: 1 | B2: tiramisu | C2: 2 | D2: =E2/2 -> 4 | E2: 8 | F2: =G2/2 -> 8 | G2: 16 | H2: =G2-E2 -> 8
A3: 2 | B3: galleta red | C3: 1 | D3: =E3/2 -> 1 | E3: 2 | F3: =G3/2 -> 2 | G3: 4 | H3: =G3-E3 -> 2
A4: 3 | B4: galleta chocolate | C4: 2 | D4: =E4/2 -> 1.5 | E4: 3 | F4: =G4/2 -> 2.5 | G4: 5 | H4: =G4-E4 -> 2
A5: 4 | B5: galleta red | C5: 2 | D5: =E5/2 -> 2 | E5: 4 | F5: =G5/2 -> 4 | G5: 8 | H5: =G5-E5 -> 4
A6: 5 | B6: galletas chocolate | C6: 2 | D6: =E6/2 -> 1.5 | E6: 3 | F6: =G6/2 -> 2.5 | G6: 5 | H6: =G6-E6 -> 2
A7: 6 | B7: cinamonroll | C7: 1 | D7: =E7/2 -> 2 | E7: 4 | F7: =G7/2 -> 4 | G7: 8 | H7: =G7-E7 -> 4
A8: 7 | B8: cheese cake cereza | C8: 1 | D8: =E8/2 -> 2 | E8: 4 | F8: =G8/2 -> 4 | G8: 8 | H8: =G8-E8 -> 4
A9: 8 | B9: Tiramisu | C9: 1 | D9: =E9/2 -> 2 | E9: 4 | F9: =G9/2 -> 4 | G9: 8 | H9: =G9-E9 -> 4
A10: 9 | B10: galletas mms chocolate | C10: 2 | D10: =E10/2 -> 2 | E10: 4 | F10: =G10/2 -> 0 | H10: =G10-E10 -> -4
A11: 6 | B11: cinamonroll | C11: 1 | D11: =E11/2 -> 2 | E11: 4 | F11: =G11/2 -> 4 | G11: 8 | H11: =G11-E11 -> 4

Sheet Compras
A1: Compra | B1: Producto | C1: Cantidad | D1: Precio U | E1: Precio
A2: 1 | B2: Maquillaje | C2: 1 | D2: 10 | E2: 10
A3: 2 | B3: Uva | C3: 1 | D3: 10 | E3: 10
A4: 3 | B4: gloss | C4: 1 | D4: 6 | E4: 6
A5: 4 | B5: lapiz ojos | C5: 1 | D5: 5.5 | E5: 5.5
A6: 5 | B6: limas | C6: 2 | D6: 2 | E6: 4
A7: 6 | B7: harina | C7: 2 | D7: 3 | E7: 6
A8: 7 | B8: huevos | C8: 1 | D8: 8 | E8: 8
A9: 8 | B9: azucar | C9: 1 | D9: 5,5 | E9: 5.5
A10: 9 | B10: mantequilla | C10: 1 | D10: 7 | E10: 7
A11: 6 | B11: harina | C11: 2 | D11: 3 | E11: 6

Sheet ETL
A1: ETL — Limpieza de datos
A2: Errores corregidos: 1 fila duplicada, 1 venta sin precio (se excluye), 1 precio con coma (azúcar) y 1 nombre con espacios/mayúsculas (Tiramisu).
A4: Ventas (limpia)
A5: id venta | B5: Producto | C5: Cantidad | D5: Costo U | E5: Costo Total | F5: Precio U | G5: Precio total | H5: Ganancia
A6: =Ventas!A2 -> 1 | B6: =LOWER(TRIM(Ventas!B2)) -> tiramisu | C6: =Ventas!C2 -> 2 | D6: =Ventas!D2 -> 4 | E6: =Ventas!E2 -> 8 | F6: =Ventas!F2 -> 8 | G6: =Ventas!G2 -> 16 | H6: =Ventas!H2 -> 8
A7: =Ventas!A3 -> 2 | B7: =LOWER(TRIM(Ventas!B3)) -> galleta red | C7: =Ventas!C3 -> 1 | D7: =Ventas!D3 -> 1 | E7: =Ventas!E3 -> 2 | F7: =Ventas!F3 -> 2 | G7: =Ventas!G3 -> 4 | H7: =Ventas!H3 -> 2
A8: =Ventas!A4 -> 3 | B8: =LOWER(TRIM(Ventas!B4)) -> galleta chocolate | C8: =Ventas!C4 -> 2 | D8: =Ventas!D4 -> 1.5 | E8: =Ventas!E4 -> 3 | F8: =Ventas!F4 -> 2.5 | G8: =Ventas!G4 -> 5 | H8: =Ventas!H4 -> 2
A9: =Ventas!A5 -> 4 | B9: =LOWER(TRIM(Ventas!B5)) -> galleta red | C9: =Ventas!C5 -> 2 | D9: =Ventas!D5 -> 2 | E9: =Ventas!E5 -> 4 | F9: =Ventas!F5 -> 4 | G9: =Ventas!G5 -> 8 | H9: =Ventas!H5 -> 4
A10: =Ventas!A6 -> 5 | B10: =LOWER(TRIM(Ventas!B6)) -> galletas chocolate | C10: =Ventas!C6 -> 2 | D10: =Ventas!D6 -> 1.5 | E10: =Ventas!E6 -> 3 | F10: =Ventas!F6 -> 2.5 | G10: =Ventas!G6 -> 5 | H10: =Ventas!H6 -> 2
A11: =Ventas!A7 -> 6 | B11: =LOWER(TRIM(Ventas!B7)) -> cinamonroll | C11: =Ventas!C7 -> 1 | D11: =Ventas!D7 -> 2 | E11: =Ventas!E7 -> 4 | F11: =Ventas!F7 -> 4 | G11: =Ventas!G7 -> 8 | H11: =Ventas!H7 -> 4
A12: =Ventas!A8 -> 7 | B12: =LOWER(TRIM(Ventas!B8)) -> cheese cake cereza | C12: =Ventas!C8 -> 1 | D12: =Ventas!D8 -> 2 | E12: =Ventas!E8 -> 4 | F12: =Ventas!F8 -> 4 | G12: =Ventas!G8 -> 8 | H12: =Ventas!H8 -> 4
A13: =Ventas!A9 -> 8 | B13: =LOWER(TRIM(Ventas!B9)) -> tiramisu | C13: =Ventas!C9 -> 1 | D13: =Ventas!D9 -> 2 | E13: =Ventas!E9 -> 4 | F13: =Ventas!F9 -> 4 | G13: =Ventas!G9 -> 8 | H13: =Ventas!H9 -> 4
A15: Compras (limpia)
A16: Compra | B16: Producto | C16: Cantidad | D16: Precio U | E16: Precio
A17: =Compras!A2 -> 1 | B17: =LOWER(TRIM(Compras!B2)) -> maquillaje | C17: =Compras!C2 -> 1 | D17: =IFERROR(VALUE(SUBSTITUTE(Compras!D2,",",".")),Compras!D2) -> 10 | E17: =Compras!E2 -> 10
A18: =Compras!A3 -> 2 | B18: =LOWER(TRIM(Compras!B3)) -> uva | C18: =Compras!C3 -> 1 | D18: =IFERROR(VALUE(SUBSTITUTE(Compras!D3,",",".")),Compras!D3) -> 10 | E18: =Compras!E3 -> 10
A19: =Compras!A4 -> 3 | B19: =LOWER(TRIM(Compras!B4)) -> gloss | C19: =Compras!C4 -> 1 | D19: =IFERROR(VALUE(SUBSTITUTE(Compras!D4,",",".")),Compras!D4) -> 6 | E19: =Compras!E4 -> 6
A20: =Compras!A5 -> 4 | B20: =LOWER(TRIM(Compras!B5)) -> lapiz ojos | C20: =Compras!C5 -> 1 | D20: =IFERROR(VALUE(SUBSTITUTE(Compras!D5,",",".")),Compras!D5) -> 5.5 | E20: =Compras!E5 -> 5.5
A21: =Compras!A6 -> 5 | B21: =LOWER(TRIM(Compras!B6)) -> limas | C21: =Compras!C6 -> 2 | D21: =IFERROR(VALUE(SUBSTITUTE(Compras!D6,",",".")),Compras!D6) -> 2 | E21: =Compras!E6 -> 4
A22: =Compras!A7 -> 6 | B22: =LOWER(TRIM(Compras!B7)) -> harina | C22: =Compras!C7 -> 2 | D22: =IFERROR(VALUE(SUBSTITUTE(Compras!D7,",",".")),Compras!D7) -> 3 | E22: =Compras!E7 -> 6
A23: =Compras!A8 -> 7 | B23: =LOWER(TRIM(Compras!B8)) -> huevos | C23: =Compras!C8 -> 1 | D23: =IFERROR(VALUE(SUBSTITUTE(Compras!D8,",",".")),Compras!D8) -> 8 | E23: =Compras!E8 -> 8
A24: =Compras!A9 -> 8 | B24: =LOWER(TRIM(Compras!B9)) -> azucar | C24: =Compras!C9 -> 1 | D24: =IFERROR(VALUE(SUBSTITUTE(Compras!D9,",",".")),Compras!D9) -> 5.5 | E24: =Compras!E9 -> 5.5
A25: =Compras!A10 -> 9 | B25: =LOWER(TRIM(Compras!B10)) -> mantequilla | C25: =Compras!C10 -> 1 | D25: =IFERROR(VALUE(SUBSTITUTE(Compras!D10,",",".")),Compras!D10) -> 7 | E25: =Compras!E10 -> 7

Sheet EDA
A1: EDA — Análisis exploratorio
A3: Ventas — resumen
A4: Unidades vendidas | B4: =SUM(ETL!C6:C13) -> 12
A5: Ingreso total (precio) | B5: =SUM(ETL!G6:G13) -> 62
A6: Costo total | B6: =SUM(ETL!E6:E13) -> 32
A7: Ganancia total | B7: =SUM(ETL!H6:H13) -> 30
A8: Ganancia promedio por venta | B8: =AVERAGE(ETL!H6:H13) -> 3.75
A10: Ganancia por producto
A11: Producto | B11: Ganancia
A12: tiramisu | B12: =SUMIF(ETL!$B$6:$B$13,A12,ETL!$H$6:$H$13) -> 12
A13: galleta red | B13: =SUMIF(ETL!$B$6:$B$13,A13,ETL!$H$6:$H$13) -> 6
A14: galleta chocolate | B14: =SUMIF(ETL!$B$6:$B$13,A14,ETL!$H$6:$H$13) -> 2
A15: galletas chocolate | B15: =SUMIF(ETL!$B$6:$B$13,A15,ETL!$H$6:$H$13) -> 2
A16: cinamonroll | B16: =SUMIF(ETL!$B$6:$B$13,A16,ETL!$H$6:$H$13) -> 4
A17: cheese cake cereza | B17: =SUMIF(ETL!$B$6:$B$13,A17,ETL!$H$6:$H$13) -> 4
A19: Compras — resumen
A20: Gasto total | B20: =SUM(ETL!E17:E25) -> 62
A22: Gasto por producto
A23: Producto | B23: Gasto
A24: maquillaje | B24: =SUMIF(ETL!$B$17:$B$25,A24,ETL!$E$17:$E$25) -> 10
A25: uva | B25: =SUMIF(ETL!$B$17:$B$25,A25,ETL!$E$17:$E$25) -> 10
A26: gloss | B26: =SUMIF(ETL!$B$17:$B$25,A26,ETL!$E$17:$E$25) -> 6
A27: lapiz ojos | B27: =SUMIF(ETL!$B$17:$B$25,A27,ETL!$E$17:$E$25) -> 5.5
A28: limas | B28: =SUMIF(ETL!$B$17:$B$25,A28,ETL!$E$17:$E$25) -> 4
A29: harina | B29: =SUMIF(ETL!$B$17:$B$25,A29,ETL!$E$17:$E$25) -> 6
A30: huevos | B30: =SUMIF(ETL!$B$17:$B$25,A30,ETL!$E$17:$E$25) -> 8
A31: azucar | B31: =SUMIF(ETL!$B$17:$B$25,A31,ETL!$E$17:$E$25) -> 5.5
A32: mantequilla | B32: =SUMIF(ETL!$B$17:$B$25,A32,ETL!$E$17:$E$25) -> 7

Sheet Conclusiones
A1: Conclusiones
A3: Hallazgo 1 | B3: El producto que más ganancia deja es el tiramisú (12 en total), seguido de la galleta red (6). Las galletas de chocolate son las que menos aportan.
A4: Hallazgo 2 | B4: La ganancia total de ventas (30) es menor que el gasto en compras (62). Además, varias compras (maquillaje, gloss, lápiz de ojos) no son de la tienda.
A5: Calidad de datos | B5: En los registros nuevos había una venta duplicada, una venta sin precio, un precio con coma (azúcar) y un nombre mal escrito (Tiramisu). Se corrigieron en la hoja ETL.
A6: Hipótesis a validar | B6: Si la tienda se concentra en tiramisú y deja de comprar cosas que no son del negocio, el balance debería mejorar.
