Workbook

Sheet Inventario
A1: Producto | B1: inventario | C1: costo | D1: venta | E1: Inventario nuevo
A2: galletas chocolate | B2: 7 | C2: 1.5 | D2: =C2*2 -> 3 | E2: =B2-Ventas!C4 -> 5
A3: galletas mms chocolate | B3: 7 | C3: 2 | D3: =C3*2 -> 4
A4: galleta red velvet chocolate | B4: 7 | C4: 2 | D4: =C4*2 -> 4 | E4: =B4-Ventas!C3 -> 6
A5: cinamonroll | B5: 2 | C5: 4 | D5: =C5*2 -> 8
A6: tiramisu | B6: 2 | C6: 4 | D6: =C6*2 -> 8 | E6: =B6-Ventas!C2 -> 0
A7: cheese cake arandanos | B7: 2 | C7: 4 | D7: =C7*2 -> 8
A8: cheese cake cereza | B8: 2 | C8: 4 | D8: =C8*2 -> 8
A11: Presupuesto inicial | B11: 50
A12: Total Ventas | B12: =SUM(Ventas!G2:G6) -> 38
A13: Total Compras | B13: =SUM(Compras!E2:E6) -> 35.5
A14: Balance final | B14: =B11+B12-B13 -> 52.5

Sheet Ventas
A1: id venta | B1: Producto | C1: Cantidad | D1: Costo U | E1: Costo Total | F1: Precio U | G1: Precio total | H1: Ganancia
A2: 1 | B2: tiramisu | C2: 2 | D2: =E2/2 -> 4 | E2: 8 | F2: =G2/2 -> 8 | G2: 16 | H2: =G2-E2 -> 8
A3: 2 | B3: galleta red | C3: 1 | D3: =E3/2 -> 1 | E3: 2 | F3: =G3/2 -> 2 | G3: 4 | H3: =G3-E3 -> 2
A4: 3 | B4: galleta chocolate | C4: 2 | D4: =E4/2 -> 1.5 | E4: 3 | F4: =G4/2 -> 2.5 | G4: 5 | H4: =G4-E4 -> 2
A5: 4 | B5: galleta red | C5: 2 | D5: =E5/2 -> 2 | E5: 4 | F5: =G5/2 -> 4 | G5: 8 | H5: =G5-E5 -> 4
A6: 5 | B6: galletas chocolate | C6: 2 | D6: =E6/2 -> 1.5 | E6: 3 | F6: =G6/2 -> 2.5 | G6: 5 | H6: =G6-E6 -> 2

Sheet Compras
A1: Compra | B1: Producto | C1: Cantidad | D1: Precio U | E1: Precio
A2: 1 | B2: Maquillaje | C2: 1 | D2: 10 | E2: 10
A3: 2 | B3: Uva | C3: 1 | D3: 10 | E3: 10
A4: 3 | B4: gloss | C4: 1 | D4: 6 | E4: 6
A5: 4 | B5: lapiz ojos | C5: 1 | D5: 5.5 | E5: 5.5
A6: 5 | B6: limas | C6: 2 | D6: 2 | E6: 4
